README.md
setup.py
pycrystal/__init__.py
pycrystal/basis_library.py
pycrystal/gaussian_basis.py
pycrystal/output.py
pycrystal.egg-info/PKG-INFO
pycrystal.egg-info/SOURCES.txt
pycrystal.egg-info/dependency_links.txt
pycrystal.egg-info/requires.txt
pycrystal.egg-info/top_level.txt