Metadata-Version: 1.2
Name: pycrystal
Version: 1.1.0
Summary: Utilities for ab initio modeling suite CRYSTAL
Home-page: https://github.com/tilde-lab/pycrystal
Author: Evgeny Blokhin, Maxim Losev, Andrey Sobolev
Author-email: support@tilde.pro
License: MIT
Keywords: materials informatics crystal structures crystal-structure crystallography CRYSTAL ab-initio ab-initio-simulations first-principles materials-science
Platform: UNKNOWN
Classifier: Development Status :: 4 - Beta
Classifier: Intended Audience :: Science/Research
Classifier: Topic :: Scientific/Engineering :: Chemistry
Classifier: Topic :: Scientific/Engineering :: Physics
Classifier: Topic :: Scientific/Engineering :: Information Analysis
Classifier: Topic :: Software Development :: Libraries :: Python Modules
Classifier: License :: OSI Approved :: MIT License
Classifier: Programming Language :: Python :: 3
Classifier: Programming Language :: Python :: 3.5
Classifier: Programming Language :: Python :: 3.6
Classifier: Programming Language :: Python :: 3.7
Classifier: Programming Language :: Python :: 3.8
Classifier: Programming Language :: Python :: 3.9
Classifier: Programming Language :: Python :: 3.10
Requires-Python: >=3.5
